SSDraw/__init__.py
SSDraw/cli.py
SSDraw/core.py
SSDraw/multi.py
ssdraw-0.2.0.dist-info/licenses/LICENSE.md
ssdraw-0.2.0.dist-info/METADATA
ssdraw-0.2.0.dist-info/WHEEL
ssdraw-0.2.0.dist-info/entry_points.txt
ssdraw-0.2.0.dist-info/top_level.txt
ssdraw-0.2.0.dist-info/RECORD
