Metadata-Version: 2.4
Name: SSDraw
Version: 0.2.0
Summary: Tool for creating publication-quality protein secondary structure diagrams
Author: Ethan Chen
Author-email: Lauren Porter <lauren.porter@nih.gov>, Pramesh Sharma <pramesh.sharma@nih.gov>
License: This software is a "United States Government Work" under the terms of the United States Copyright Act. It was written as part of the authors' official duties as United States Government employees and thus cannot be copyrighted. This software is freely available to the public for use. The National Library of Medicine and the U.S. Government have not placed any restriction on its use or reproduction.
License-File: LICENSE.md
Requires-Dist: biopython>=1.81
Requires-Dist: numpy>=1.24
Requires-Dist: matplotlib>=3.7
Requires-Dist: torch>=2.0.1
Requires-Dist: pydssp
Dynamic: license-file
